ColoreRegioni/__init__.py
ColoreRegioni-0.2.0.dist-info/LICENSE
ColoreRegioni-0.2.0.dist-info/METADATA
ColoreRegioni-0.2.0.dist-info/WHEEL
ColoreRegioni-0.2.0.dist-info/top_level.txt
ColoreRegioni-0.2.0.dist-info/RECORD
