Metadata-Version: 2.1
Name: ColoreRegioni
Version: 0.2.0
Summary: Web-scraping del sito del governo italiano per la classificazione delle misure restrittive regionali
Home-page: https://github.com/MCilento93/ColoreRegioni
Author: Mario Cilento
Author-email: mario.cilento.93@gmail.com
License: MIT
Platform: UNKNOWN
Classifier: Programming Language :: Python :: 3.8
Classifier: License :: OSI Approved :: MIT License
Classifier: Operating System :: OS Independent
Requires-Dist: beautifulsoup4
